mup_tf/__init__.py
mup_tf/coord_check.py
mup_tf/infshape.py
mup_tf/layer.py
mup_tf/optimizer.py
mup_tf/shape.py
mup_tf-0.0.3.dist-info/LICENSE
mup_tf-0.0.3.dist-info/METADATA
mup_tf-0.0.3.dist-info/WHEEL
mup_tf-0.0.3.dist-info/top_level.txt
mup_tf-0.0.3.dist-info/RECORD
