Metadata-Version: 2.1
Name: mup-tf
Version: 0.0.3
Summary: Maximal Update Parametrization in Tensorflow
Home-page: https://github.com/zanussbaum/mup-tf
Author: Zach Nussbaum
Author-email: zanussbaum@gmail.com
License: PROPRIETARY
Classifier: Development Status :: 3 - Alpha
Classifier: License :: Other/Proprietary License
Classifier: Programming Language :: Python :: 3.8
Requires-Python: >=3.7, <4
License-File: LICENSE
Requires-Dist: tensorflow (<2.10.0)
Requires-Dist: tqdm
Requires-Dist: pyyaml
Requires-Dist: matplotlib
Requires-Dist: seaborn
